[{"ansible_loop_var": "item", "changed": false, "cmd": ["kubectl", "apply", "-f", "https://raw.githubusercontent.com/coreos/flannel/master/Documentation/k8s-manifests/kube-flannel-rbac.yml"], "delta": "0:00:01.684567", "end": "2022-06-07 05:12:44.147079", "item": "kubectl apply -f https://raw.githubusercontent.com/coreos/flannel/master/Documentation/k8s-manifests/kube-flannel-rbac.yml", "msg": "non-zero return code", "rc": 1, "start": "2022-06-07 05:12:42.462512", "stderr": "Unable to connect to the server: dial tcp 192.168.2.41:6443: connect: no route to host", "stderr_lines": ["Unable to connect to the server: dial tcp 192.168.2.41:6443: connect: no route to host"], "stdout": "", "stdout_lines": []},
{"ansible_loop_var": "item", "changed": false, "cmd": ["kubectl", "apply", "-f", "https://raw.githubusercontent.com/coreos/flannel/master/Documentation/k8s-manifests/kube-flannel-rbac.yml"], "delta": "0:00:10.149035", "end": "2022-06-07 05:25:17.347135", "item": "kubectl apply -f https://raw.githubusercontent.com/coreos/flannel/master/Documentation/k8s-manifests/kube-flannel-rbac.yml", "msg": "non-zero return code", "rc": 1, "start": "2022-06-07 05:25:07.198100", "stderr": "Unable to connect to the server: net/http: TLS handshake timeout", "stderr_lines": ["Unable to connect to the server: net/http: TLS handshake timeout"], "stdout": "", "stdout_lines": []}
]